[
  [
    [
      "124",
      "Paolo Facchini"
    ],
    {
      "reach": "74.486014 km",
      "frac": 1
    }
  ],
  [
    [
      "180",
      "Michal Gierlach"
    ],
    {
      "reach": "74.486014 km",
      "frac": 1
    }
  ],
  [
    [
      "175",
      "Mariusz Wisniowski"
    ],
    {
      "reach": "74.486014 km",
      "frac": 1
    }
  ],
  [
    [
      "106",
      "Christian Biasi"
    ],
    {
      "reach": "74.486014 km",
      "frac": 1
    }
  ],
  [
    [
      "146",
      "Joachim Oberhauser"
    ],
    {
      "reach": "74.486014 km",
      "frac": 1
    }
  ],
  [
    [
      "159",
      "Krzysztof Schmidt"
    ],
    {
      "reach": "74.486014 km",
      "frac": 1
    }
  ],
  [
    [
      "115",
      "Alberto Castagna"
    ],
    {
      "reach": "74.486014 km",
      "frac": 1
    }
  ],
  [
    [
      "172",
      "Alessio Voltan"
    ],
    {
      "reach": "74.486014 km",
      "frac": 1
    }
  ],
  [
    [
      "127",
      "Richárd Gabrieli"
    ],
    {
      "reach": "74.486014 km",
      "frac": 1
    }
  ],
  [
    [
      "177",
      "Bogdan Bialka"
    ],
    {
      "reach": "74.486014 km",
      "frac": 1
    }
  ],
  [
    [
      "132",
      "Jacek Górski"
    ],
    {
      "reach": "74.486014 km",
      "frac": 1
    }
  ],
  [
    [
      "112",
      "Silvia Buzzi Ferraris"
    ],
    {
      "reach": "74.486014 km",
      "frac": 1
    }
  ],
  [
    [
      "155",
      "Alfio Ragaglia"
    ],
    {
      "reach": "74.486014 km",
      "frac": 1
    }
  ],
  [
    [
      "117",
      "Gianfranco Crestani"
    ],
    {
      "reach": "74.486014 km",
      "frac": 1
    }
  ],
  [
    [
      "137",
      "Slawomir Kaczynski"
    ],
    {
      "reach": "74.486014 km",
      "frac": 1
    }
  ],
  [
    [
      "109",
      "Federico Brown Manzone"
    ],
    {
      "reach": "74.486014 km",
      "frac": 1
    }
  ],
  [
    [
      "168",
      "Marco Valentini"
    ],
    {
      "reach": "74.486014 km",
      "frac": 1
    }
  ],
  [
    [
      "154",
      "Stefano Pucci"
    ],
    {
      "reach": "74.486014 km",
      "frac": 1
    }
  ],
  [
    [
      "138",
      "Marco Littamè"
    ],
    {
      "reach": "74.486014 km",
      "frac": 1
    }
  ],
  [
    [
      "111",
      "Marco Busetta"
    ],
    {
      "reach": "74.486014 km",
      "frac": 1
    }
  ],
  [
    [
      "142",
      "Luca Mammucari"
    ],
    {
      "reach": "74.486014 km",
      "frac": 1
    }
  ],
  [
    [
      "173",
      "Paolo Zammarchi"
    ],
    {
      "reach": "74.486014 km",
      "frac": 1
    }
  ],
  [
    [
      "157",
      "Elio Rossi"
    ],
    {
      "reach": "74.486014 km",
      "frac": 1
    }
  ],
  [
    [
      "171",
      "Biagio Alberto Vitale"
    ],
    {
      "reach": "74.486014 km",
      "frac": 1
    }
  ],
  [
    [
      "150",
      "Luca Paoletti"
    ],
    {
      "reach": "74.486014 km",
      "frac": 1
    }
  ],
  [
    [
      "126",
      "Alessandro Fuzzi"
    ],
    {
      "reach": "74.486014 km",
      "frac": 1
    }
  ],
  [
    [
      "145",
      "Federico Nevastro"
    ],
    {
      "reach": "74.486014 km",
      "frac": 1
    }
  ],
  [
    [
      "156",
      "Massimo Rapari"
    ],
    {
      "reach": "74.486014 km",
      "frac": 1
    }
  ],
  [
    [
      "164",
      "Anca Tabara"
    ],
    {
      "reach": "74.486014 km",
      "frac": 1
    }
  ],
  [
    [
      "170",
      "Paolo Veratti"
    ],
    {
      "reach": "74.486014 km",
      "frac": 1
    }
  ],
  [
    [
      "116",
      "Ivan Centa"
    ],
    {
      "reach": "74.486014 km",
      "frac": 1
    }
  ],
  [
    [
      "105",
      "Daniele Bevilacqua"
    ],
    {
      "reach": "74.486014 km",
      "frac": 1
    }
  ],
  [
    [
      "148",
      "Luciano Pagnoni"
    ],
    {
      "reach": "74.486014 km",
      "frac": 1
    }
  ],
  [
    [
      "141",
      "Albino Malli"
    ],
    {
      "reach": "74.486014 km",
      "frac": 1
    }
  ],
  [
    [
      "102",
      "Matteo Bacchiocchi"
    ],
    {
      "reach": "74.486014 km",
      "frac": 1
    }
  ],
  [
    [
      "178",
      "Marius Saigiu"
    ],
    {
      "reach": "74.486014 km",
      "frac": 1
    }
  ],
  [
    [
      "174",
      "Davide Zaltron"
    ],
    {
      "reach": "74.486014 km",
      "frac": 1
    }
  ],
  [
    [
      "121",
      "Giorgio Darra"
    ],
    {
      "reach": "74.486014 km",
      "frac": 1
    }
  ],
  [
    [
      "153",
      "Gianbasilio Profiti"
    ],
    {
      "reach": "74.486014 km",
      "frac": 1
    }
  ],
  [
    [
      "166",
      "Tiziano Trambaioli"
    ],
    {
      "reach": "74.486014 km",
      "frac": 1
    }
  ],
  [
    [
      "101",
      "Diego Ardissone"
    ],
    {
      "reach": "74.486014 km",
      "frac": 1
    }
  ],
  [
    [
      "162",
      "Arkadiusz Slusarczyk"
    ],
    {
      "reach": "74.486014 km",
      "frac": 1
    }
  ],
  [
    [
      "151",
      "Piergiorgio Pintossi"
    ],
    {
      "reach": "74.486014 km",
      "frac": 1
    }
  ],
  [
    [
      "169",
      "Alessandro Vallero"
    ],
    {
      "reach": "74.486014 km",
      "frac": 1
    }
  ],
  [
    [
      "129",
      "Luciano Gallo"
    ],
    {
      "reach": "74.486014 km",
      "frac": 1
    }
  ],
  [
    [
      "130",
      "Andrea Garolla"
    ],
    {
      "reach": "74.486014 km",
      "frac": 1
    }
  ],
  [
    [
      "143",
      "Valerio Marchetti"
    ],
    {
      "reach": "74.486014 km",
      "frac": 1
    }
  ],
  [
    [
      "136",
      "Gbriel-Alexandru Ivan"
    ],
    {
      "reach": "74.486014 km",
      "frac": 1
    }
  ],
  [
    [
      "135",
      "Cristian Inverardi"
    ],
    {
      "reach": "72.815014 km",
      "frac": 0.97756626
    }
  ],
  [
    [
      "133",
      "Alessio Guidi"
    ],
    {
      "reach": "72.618014 km",
      "frac": 0.97492147
    }
  ],
  [
    [
      "139",
      "Alessandro Madaluni"
    ],
    {
      "reach": "71.752014 km",
      "frac": 0.96329512
    }
  ],
  [
    [
      "113",
      "Tommaso Carlini"
    ],
    {
      "reach": "69.147014 km",
      "frac": 0.92832211
    }
  ],
  [
    [
      "108",
      "Michele Boschi"
    ],
    {
      "reach": "69.121014 km",
      "frac": 0.92797306
    }
  ],
  [
    [
      "147",
      "Francesco Orcese"
    ],
    {
      "reach": "69.059014 km",
      "frac": 0.92714068
    }
  ],
  [
    [
      "158",
      "Antonio Ruta"
    ],
    {
      "reach": "66.796014 km",
      "frac": 0.89675914
    }
  ],
  [
    [
      "122",
      "Angelo Dell’Aira"
    ],
    {
      "reach": "65.939014 km",
      "frac": 0.88525363
    }
  ],
  [
    [
      "144",
      "Riccardo Marchetto"
    ],
    {
      "reach": "65.277014 km",
      "frac": 0.87636605
    }
  ],
  [
    [
      "161",
      "Matteo Siragna"
    ],
    {
      "reach": "65.202014 km",
      "frac": 0.87535915
    }
  ],
  [
    [
      "176",
      "Francesco Fontanesi"
    ],
    {
      "reach": "60.545014 km",
      "frac": 0.81283735
    }
  ],
  [
    [
      "152",
      "Alessandro Pompei"
    ],
    {
      "reach": "59.727014 km",
      "frac": 0.80185542
    }
  ],
  [
    [
      "149",
      "Alessandro Palma"
    ],
    {
      "reach": "54.621014 km",
      "frac": 0.73330564
    }
  ],
  [
    [
      "160",
      "Giuseppe Simone"
    ],
    {
      "reach": "54.009014 km",
      "frac": 0.72508933
    }
  ],
  [
    [
      "131",
      "Marco Gentilini"
    ],
    {
      "reach": "53.945014 km",
      "frac": 0.72423011
    }
  ],
  [
    [
      "165",
      "Andrea Terenziani"
    ],
    {
      "reach": "53.942014 km",
      "frac": 0.72418983
    }
  ],
  [
    [
      "167",
      "Ionut Ulici"
    ],
    {
      "reach": "48.058014 km",
      "frac": 0.64519514
    }
  ],
  [
    [
      "107",
      "Gabriele Bonafini"
    ],
    {
      "reach": "42.750014 km",
      "frac": 0.57393344
    }
  ],
  [
    [
      "120",
      "Gabriele D'Arrigo"
    ],
    {
      "reach": "27.997014 km",
      "frac": 0.37586941
    }
  ],
  [
    [
      "114",
      "Mirco Casarini"
    ],
    {
      "reach": "25.675014 km",
      "frac": 0.34469577
    }
  ],
  [
    [
      "125",
      "Grzegorz Fiema"
    ],
    {
      "reach": "21.386014 km",
      "frac": 0.28711449
    }
  ],
  [
    [
      "104",
      "Loris Berta"
    ],
    {
      "reach": "18.770014 km",
      "frac": 0.2519938
    }
  ],
  [
    [
      "140",
      "Maurizio Maina"
    ],
    {
      "reach": "18.661014 km",
      "frac": 0.25053044
    }
  ],
  [
    [
      "110",
      "Klaudia Bulgakow"
    ],
    {
      "reach": "17.781014 km",
      "frac": 0.23871614
    }
  ],
  [
    [
      "128",
      "Michele Gaiba"
    ],
    {
      "reach": "17.137014 km",
      "frac": 0.23007022
    }
  ],
  [
    [
      "118",
      "Igor D'Agostino"
    ],
    {
      "reach": "13.352014 km",
      "frac": 0.17925532
    }
  ],
  [
    [
      "123",
      "Sergio Di Fazio"
    ],
    {
      "reach": "9.494014 km",
      "frac": 0.12746036
    }
  ],
  [
    [
      "119",
      "Maria Antonietta D'Angela"
    ],
    {
      "reach": "7.892014 km",
      "frac": 0.10595296
    }
  ]
]
